iotile/__init__.py
iotile/cloud/__init__.py
iotile/cloud/cloud.py
iotile/cloud/config.py
iotile/cloud/plugin.py
iotile/cloud/utilities.py
iotile/cloud/apps/__init__.py
iotile/cloud/apps/cloud_uploader.py
iotile/cloud/apps/ota_updater.py
iotile_ext_cloud-1.2.0.dist-info/LICENSE.md
iotile_ext_cloud-1.2.0.dist-info/METADATA
iotile_ext_cloud-1.2.0.dist-info/WHEEL
iotile_ext_cloud-1.2.0.dist-info/entry_points.txt
iotile_ext_cloud-1.2.0.dist-info/top_level.txt
iotile_ext_cloud-1.2.0.dist-info/RECORD
